zotlink/__init__.py
zotlink/cli.py
zotlink/zotero_integration.py
zotlink/zotero_mcp_server.py
zotlink/browser_bookmarks/zotlink_sync_bookmarklet.js
zotlink/cookie_sync/__init__.py
zotlink/cookie_sync/cookie_receiver.py
zotlink/cookie_sync/database_registry.py
zotlink/cookie_sync/sync_manager.py
zotlink/extractors/__init__.py
zotlink/extractors/base_extractor.py
zotlink/extractors/biorxiv_direct_extractor.py
zotlink/extractors/browser_extractor.py
zotlink/extractors/cvf_extractor.py
zotlink/extractors/enhanced_generic_extractor.py
zotlink/extractors/extractor_manager.py
zotlink/extractors/generic_extractor.py
zotlink/extractors/nature_extractor.py
zotlink/extractors/preprint_extractor.py
zotlink-1.3.8.dist-info/METADATA
zotlink-1.3.8.dist-info/WHEEL
zotlink-1.3.8.dist-info/entry_points.txt
zotlink-1.3.8.dist-info/top_level.txt
zotlink-1.3.8.dist-info/RECORD
